MANIFEST.in
README.rst
flake8.ini
pylint.ini
setup.py
tox.ini
bin/txclean
bin/txcopy
bin/txdocs
bin/txredirect
docs/Makefile
docs/source/conf.py
docs/source/index.rst
docs/source/macros.txt
docs/source/reference/modules.rst
docs/source/reference/toxins.rst
docs/source/reference/toxins.version.rst
docs/source/templates/module.rst
docs/source/templates/package.rst
docs/source/templates/toc.rst
requirements/docs.txt
requirements/flake8.txt
requirements/install.txt
requirements/pylint.txt
requirements/tests.txt
toxins/__init__.py
toxins/version.py
toxins.egg-info/PKG-INFO
toxins.egg-info/SOURCES.txt
toxins.egg-info/dependency_links.txt
toxins.egg-info/top_level.txt