Metadata-Version: 1.1
Name: toxins
Version: 0.3.0
Summary: Tools for tox projects
Home-page: UNKNOWN
Author: Simone Campagna
Author-email: simone.campagna11@gmail.com
License: UNKNOWN
Keywords: tox project tools
Platform: UNKNOWN
Classifier: Development Status :: 4 - Beta
Classifier: Intended Audience :: Developers
Classifier: Topic :: Software Development :: Testing
Classifier: License :: OSI Approved :: Apache Software License
Classifier: Programming Language :: Python :: 3.4
